{
	"id": "delivery-api-environment",
	"name": "Delivery API - Local",
	"values": [
		{
			"key": "base_url",
			"value": "http://localhost:8080",
			"type": "default",
			"enabled": true
		},
		{
			"key": "keycloak_url",
			"value": "http://localhost:8081",
			"type": "default",
			"enabled": true
		},
		{
			"key": "access_token",
			"value": "",
			"type": "secret",
			"enabled": true
		},
		{
			"key": "customer_id",
			"value": "",
			"type": "default",
			"enabled": true
		},
		{
			"key": "product_id",
			"value": "",
			"type": "default",
			"enabled": true
		},
		{
			"key": "order_id",
			"value": "",
			"type": "default",
			"enabled": true
		}
	],
	"_postman_variable_scope": "environment"
}
